mkdocs_wordart/plugin.py
mkdocs_wordart/assets/wordart.css
mkdocs_wordart/templates/wordart.html
mkdocs_wordart-0.1.2.dist-info/LICENSE
mkdocs_wordart-0.1.2.dist-info/METADATA
mkdocs_wordart-0.1.2.dist-info/WHEEL
mkdocs_wordart-0.1.2.dist-info/entry_points.txt
mkdocs_wordart-0.1.2.dist-info/top_level.txt
mkdocs_wordart-0.1.2.dist-info/RECORD
