Metadata-Version: 2.1
Name: mkdocs-wordart
Version: 0.1.2
Summary: A MkDocs plugin that makes wordart available again.
Author-email: Useless DevLab <useless.devlab@gmail.com>
License: MIT License
Project-URL: Documentation, https://Useless-DevLab.github.io/mkdocs-wordart/
Project-URL: Issues, https://github.com/Useless-DevLab/mkdocs-wordart/issues
Project-URL: Source, https://github.com/Useless-DevLab/mkdocs-wordart
Keywords: mkdocs,documentation,wordart
Classifier: Development Status :: 3 - Alpha
Classifier: Environment :: Console
Classifier: Operating System :: POSIX
Classifier: Intended Audience :: Developers
Classifier: Intended Audience :: Information Technology
Classifier: Intended Audience :: System Administrators
Classifier: Topic :: Software Development :: Build Tools
Classifier: Natural Language :: English
Classifier: Programming Language :: Python :: 3.9
Classifier: Programming Language :: Python :: 3.10
Classifier: Programming Language :: Python :: 3.11
Classifier: Programming Language :: Python :: 3.12
Classifier: Topic :: Utilities
Classifier: Topic :: Software Development :: Documentation
Requires-Python: >=3.9
License-File: LICENSE
Requires-Dist: mkdocs >=1.5.3
